PlumedToHTML/PlumedCLFileLexer.py
PlumedToHTML/PlumedCLtoolLexer.py
PlumedToHTML/PlumedFormatter.py
PlumedToHTML/PlumedLexer.py
PlumedToHTML/PlumedToHTML.py
PlumedToHTML/__init__.py
PlumedToHTML/assets/header.html
plumedtohtml-0.125.dist-info/licenses/LICENSE
plumedtohtml-0.125.dist-info/METADATA
plumedtohtml-0.125.dist-info/WHEEL
plumedtohtml-0.125.dist-info/top_level.txt
plumedtohtml-0.125.dist-info/RECORD
