Metadata-Version: 2.4
Name: PlumedToHTML
Version: 0.125
Summary: A package for creating prettified HTML for PLUMED files
Author-email: Gareth Tribello <gareth.tribello@gmail.com>
Maintainer-email: Daniele Rapetti <iximiel@gmail.com>
License: LGPL-2.1-only
Project-URL: Repository, https://github.com/plumed/PlumedToHTML
Project-URL: PLUMED Website, https://www.plumed.org/
Keywords: PLUMED,HTML,developer,documentation,prettified
Classifier: Development Status :: 4 - Beta
Classifier: License :: OSI Approved :: GNU Lesser General Public License v2 or later (LGPLv2+)
Classifier: Operating System :: POSIX :: Linux
Classifier: Operating System :: MacOS
Classifier: Programming Language :: Python :: 3
Classifier: Programming Language :: Python :: 3.8
Classifier: Programming Language :: Python :: 3.9
Classifier: Programming Language :: Python :: 3.10
Classifier: Programming Language :: Python :: 3.11
Classifier: Programming Language :: Python :: 3.12
Classifier: Programming Language :: Python :: 3.13
Classifier: Framework :: tox
Classifier: Framework :: Pytest
Classifier: Topic :: Text Processing :: Markup :: HTML
Classifier: Intended Audience :: Developers
Classifier: Intended Audience :: Science/Research
Requires-Python: >=3.8
License-File: LICENSE
Requires-Dist: bs4
Requires-Dist: lxml
Requires-Dist: pygments
Requires-Dist: requests
Dynamic: license-file
